{
  "lastCrawl": "2026-04-23T23:36:31.895539",
  "sources": {
    "contestkorea": {
      "lastSuccess": "2026-04-23T23:36:33.388176",
      "count": 13,
      "errors": []
    },
    "thinkcontest": {
      "lastSuccess": "2026-04-23T23:36:36.440398",
      "count": 0,
      "errors": []
    },
    "linkareer": {
      "lastSuccess": "2026-04-23T23:36:48.665945",
      "count": 3,
      "errors": []
    },
    "wevity": {
      "lastSuccess": "2026-04-23T23:37:26.580455",
      "count": 14,
      "errors": []
    },
    "dacon": {
      "lastSuccess": "2026-04-23T23:37:27.924787",
      "count": 15,
      "errors": []
    }
  }
}