{
  "lastCrawl": "2026-03-30T23:26:47.290408",
  "sources": {
    "contestkorea": {
      "lastSuccess": "2026-03-30T23:26:49.364249",
      "count": 13,
      "errors": []
    },
    "thinkcontest": {
      "lastSuccess": "2026-03-30T23:26:53.436869",
      "count": 2,
      "errors": []
    },
    "linkareer": {
      "lastSuccess": "2026-03-30T23:27:06.281775",
      "count": 4,
      "errors": []
    },
    "wevity": {
      "lastSuccess": "2026-03-30T23:27:49.868146",
      "count": 7,
      "errors": []
    },
    "dacon": {
      "lastSuccess": "2026-03-30T23:27:51.482240",
      "count": 15,
      "errors": []
    }
  }
}