{
  "lastCrawl": "2026-03-17T23:23:03.575747",
  "sources": {
    "contestkorea": {
      "lastSuccess": "2026-03-17T23:23:05.992637",
      "count": 12,
      "errors": []
    },
    "thinkcontest": {
      "lastSuccess": "2026-03-17T23:23:09.111298",
      "count": 0,
      "errors": []
    },
    "linkareer": {
      "lastSuccess": "2026-03-17T23:23:35.842473",
      "count": 2,
      "errors": []
    },
    "wevity": {
      "lastSuccess": "2026-03-17T23:24:14.694482",
      "count": 5,
      "errors": []
    },
    "dacon": {
      "lastSuccess": "2026-03-17T23:24:16.320444",
      "count": 15,
      "errors": []
    }
  }
}